lms_geotool/__init__.py
lms_geotool/admin.py
lms_geotool/apps.py
lms_geotool/models.py
lms_geotool/tests.py
lms_geotool/urls.py
lms_geotool/views.py
lms_geotool/migrations/__init__.py
lms_geotool/static/lms_geotool/css/lib/element-plus.css
lms_geotool/static/lms_geotool/js/lib/echarts/echarts.min.js
lms_geotool/static/lms_geotool/js/lib/element/dayjs.min.js
lms_geotool/static/lms_geotool/js/lib/element/element-plus.min.js
lms_geotool/static/lms_geotool/js/lib/element/zh-cn.js
lms_geotool/static/lms_geotool/js/lib/vue/vue.global.prod.js
lms_geotool/templates/common.html
lms_geotool/templates/lms_geotool/convert.html
lms_geotool/templates/lms_geotool/dimsum.html
lms_geotool/templates/lms_geotool/matrix.html
lms_geotool/templates/lms_geotool/regression.html
lms_geotool/templates/lms_geotool/translation.html
lms_geotool/tools/__init__.py
lms_geotool/tools/geographic.py
lms_geotool/tools/matrix.py
lms_geotool/tools/projected.py
lms_geotool-1.3.0.dist-info/licenses/LICENSE
lms_geotool-1.3.0.dist-info/METADATA
lms_geotool-1.3.0.dist-info/WHEEL
lms_geotool-1.3.0.dist-info/top_level.txt
lms_geotool-1.3.0.dist-info/RECORD
